danksearch/__init__.py
danksearch/backupcode.py
danksearch/safesearchfilter.txt
danksearch-0.1.2.dist-info/LICENSE
danksearch-0.1.2.dist-info/METADATA
danksearch-0.1.2.dist-info/WHEEL
danksearch-0.1.2.dist-info/top_level.txt
danksearch-0.1.2.dist-info/RECORD
