Metadata-Version: 2.1
Name: danksearch
Version: 0.1.2
Summary: An async youtube search library made for use with discord.py
Home-page: https://github.com/actualdankcoder/danksearch-discord
Author: DankCoder
Author-email: business.dankcoder@gmail.com
License: UNKNOWN
Platform: UNKNOWN
Classifier: Programming Language :: Python :: 3
Classifier: License :: OSI Approved :: MIT License
Classifier: Operating System :: OS Independent
Requires-Python: >=3.6
Requires-Dist: aiohttp
Requires-Dist: lxml
